Metadata-Version: 1.0
Name: jenny-udacity-distributions
Version: 0.1
Summary: Gaussian and Bionomial distributions
Home-page: UNKNOWN
Author: UNKNOWN
Author-email: UNKNOWN
License: UNKNOWN
Platform: UNKNOWN
